skia_harfbuzz/__init__.py
skia_harfbuzz/config.py
skia_harfbuzz/font.py
skia_harfbuzz/patching.py
skia_harfbuzz/shaping.py
skia_harfbuzz/util.py
skia_harfbuzz-0.1.0.dist-info/licenses/LICENSE
skia_harfbuzz-0.1.0.dist-info/METADATA
skia_harfbuzz-0.1.0.dist-info/WHEEL
skia_harfbuzz-0.1.0.dist-info/top_level.txt
skia_harfbuzz-0.1.0.dist-info/RECORD
