Metadata-Version: 2.4
Name: skia-harfbuzz
Version: 0.1.0
Summary: Utilities for skia-python to shape and draw text with harfbuzz
Author-email: Rosemoe <rosemoe168@gmail.com>
License-Expression: Apache-2.0
Project-URL: Homepage, https://github.com/Rosemoe/skia-harfbuzz
Classifier: Development Status :: 4 - Beta
Classifier: Operating System :: MacOS :: MacOS X
Classifier: Operating System :: Microsoft :: Windows
Classifier: Operating System :: POSIX
Classifier: Topic :: Multimedia :: Graphics
Classifier: Intended Audience :: Developers
Classifier: Programming Language :: Python :: 3
Requires-Python: >=3.8
License-File: LICENSE
Requires-Dist: skia-python>=87.7
Requires-Dist: uharfbuzz>=0.51.0
Dynamic: license-file
